hxfile/__main__.py
hxfile/__meta__.py
hxfile/hxfile.py
hxfile/logger.py
hxfile-0.15.dist-info/METADATA
hxfile-0.15.dist-info/WHEEL
hxfile-0.15.dist-info/entry_points.txt
hxfile-0.15.dist-info/top_level.txt
hxfile-0.15.dist-info/RECORD
