Metadata-Version: 2.1
Name: hxfile
Version: 0.15
Summary: unofficial HXFILE API (still maintenance, open contributor)
Home-page: https://github.com/cumulus13/hxfile
Download-URL: https://github.com/cumulus13/hxfile/tarball/master
Author: Hadi Cahyadi LD
Author-email: cumulus13@gmail.com
License: MIT License
Keywords: hxfile,api,unoffcial,link generator,generator,download,downloader,cloud,file manager,cli,command line,unofficial HXFILE API (still maintenance, open contributor
Platform: UNKNOWN
Classifier: Development Status :: 5 - Production/Stable
Classifier: Environment :: Console
Classifier: Intended Audience :: Developers
Classifier: License :: OSI Approved :: MIT License
Classifier: Operating System :: OS Independent
Classifier: Programming Language :: Python
Classifier: Programming Language :: Python :: 2
Classifier: Programming Language :: Python :: 3
Classifier: Topic :: Software Development :: Libraries :: Python Modules
Requires-Python: >=2.7
Requires-Dist: unidecode
Requires-Dist: configset
Requires-Dist: parserheader
Requires-Dist: requests
Requires-Dist: bs4
Requires-Dist: bitmath
Requires-Dist: clipboard
Requires-Dist: make-colors
